telegather/__init__.py
telegather/cli.py
telegather/scraper.py
telegather-0.1.4.dist-info/licenses/LICENSE
telegather-0.1.4.dist-info/METADATA
telegather-0.1.4.dist-info/WHEEL
telegather-0.1.4.dist-info/entry_points.txt
telegather-0.1.4.dist-info/top_level.txt
telegather-0.1.4.dist-info/RECORD
