Metadata-Version: 2.4
Name: telegather
Version: 0.1.4
Summary: CLI tool to scrape messages from a Telegram channel into CSV.
Home-page: https://github.com/Endale2/telegather
Author: Endale Shimelis
Author-email: endale406@gmail.com
License: MIT
Classifier: Programming Language :: Python :: 3
Classifier: License :: OSI Approved :: MIT License
Classifier: Operating System :: OS Independent
Requires-Python: >=3.7
Requires-Dist: telethon>=1.28.0
Requires-Dist: colorama>=0.4.6
